d3dshot/__init__.py
d3dshot/_compat.py
d3dshot/capture_output.py
d3dshot/d3dshot.py
d3dshot/display.py
d3dshot/py.typed
d3dshot/capture_outputs/__init__.py
d3dshot/capture_outputs/numpy_capture_output.py
d3dshot/capture_outputs/numpy_float_capture_output.py
d3dshot/capture_outputs/pil_capture_output.py
d3dshot/capture_outputs/pytorch_capture_output.py
d3dshot/capture_outputs/pytorch_float_capture_output.py
d3dshot/capture_outputs/pytorch_float_gpu_capture_output.py
d3dshot/capture_outputs/pytorch_gpu_capture_output.py
d3dshot/dll/__init__.py
d3dshot/dll/d3d.py
d3dshot/dll/dxgi.py
d3dshot/dll/shcore.py
d3dshot/dll/user32.py
typed_D3DShot-1.0.1.dist-info/LICENSE
typed_D3DShot-1.0.1.dist-info/METADATA
typed_D3DShot-1.0.1.dist-info/WHEEL
typed_D3DShot-1.0.1.dist-info/top_level.txt
typed_D3DShot-1.0.1.dist-info/RECORD
