Metadata-Version: 2.1
Name: typed-D3DShot
Version: 1.0.1
Summary: Extremely Fast, Robust, and Typed, Screen Capture on Windows with the Desktop Duplication API
Author-email: Nicholas Brochu <nicholas@serpent.ai>
Maintainer-email: Avasam <samuel.06@hotmail.com>
License: MIT License
Project-URL: Homepage, https://github.com/Avasam/D3DShot
Project-URL: Repository, https://github.com/Avasam/D3DShot.git
Project-URL: Issues, https://github.com/Avasam/D3DShot/issues
Project-URL: Changelog, https://github.com/Avasam/D3DShot/blob/HEAD/CHANGELOG.md
Keywords: Computer Vision,D3D,Desktop Duplication,Direct3D,Screen Capture,Screenshot,Windows
Classifier: Development Status :: 4 - Beta
Classifier: Intended Audience :: Developers
Classifier: License :: OSI Approved :: MIT License
Classifier: Natural Language :: English
Classifier: Operating System :: Microsoft :: Windows
Classifier: Operating System :: Microsoft :: Windows :: Windows 8.1
Classifier: Operating System :: Microsoft :: Windows :: Windows 10
Classifier: Operating System :: Microsoft :: Windows :: Windows 11
Classifier: Programming Language :: Python
Classifier: Programming Language :: Python :: 3.8
Classifier: Programming Language :: Python :: 3.9
Classifier: Programming Language :: Python :: 3.10
Classifier: Programming Language :: Python :: 3.11
Classifier: Programming Language :: Python :: 3.12
Classifier: Programming Language :: Python :: 3.13
Classifier: Topic :: Multimedia :: Graphics
Classifier: Topic :: Multimedia :: Graphics :: Capture
Classifier: Topic :: Multimedia :: Graphics :: Capture :: Screen Capture
Requires-Python: >=3.8
License-File: LICENSE
Requires-Dist: comtypes >=1.1.7
Provides-Extra: pil
Requires-Dist: pillow >=9.1.0 ; extra == 'pil'
Provides-Extra: dev
Requires-Dist: ruff ~=0.6.9 ; extra == 'dev'
Requires-Dist: mypy ==1.11.* ; extra == 'dev'
Requires-Dist: pyright ==1.1.384 ; extra == 'dev'
Provides-Extra: numpy
Requires-Dist: numpy >=1.21.0 ; extra == 'numpy'
Provides-Extra: torch
Requires-Dist: torch >=2.0.0 ; extra == 'torch'
Requires-Dist: typed-D3DShot[numpy] ; extra == 'torch'
